{
  "metadata": {
    "source": "pdf_analysis",
    "created": "2025-12-11T00:55:04.350038",
    "file_path": "/Users/machine/Documents/kettler-data-analysis/research/texas/pdf_analysis/MERGED-Kettler/pages/page_2240.json",
    "has_embedding": true
  },
  "data": {
    "page_number": 2240,
    "text": "1310210013\n1310210013\n0T42776-7Ka halaR eastuLLCra ...ns,t EMNSYSTO ITCRR OPOACT 00\n0T42781-7Bro adostneL aurelH ighlanLd Ls,C EMNSYSTO ITCRR OPOACT 00\niaDst esignBu ilLd L,C0T42782-5V EMNSYSTO ITCRR OPOACT 00\nAllianceC ommuniiLte Ls,C0T42784-1 EMNSYSTO ITCRR OPOACT 00\n0T42787-4 RaPoweLr-3 L,C EMNSYSTO ITCRR OPOACT 00\n0T42792h-4Wie tcoR esidenitalMa nageLme Ln,Ct EMNSYSTO ITCRR OPOACT 00\nCLVIES LCSER AMT0T42801-3 NICENS AGTERSTEDRI EGNOALITNA 00\n0T42803kuL-9In L ,C EMNSYSTO ITCRR OPOACT 00\nL LC0T42807-0PRMARSEC OK UYRTI EMNSYSTO ITCRR OPOACT 00\nLL LGEBE,CAX RAIFF 0T42809-6C PT EMNSYSTO ITCRR OPOACT 00\nioctriainFn anLce L,C0T42814-6V EMNSYSTO ITCRR OPOACT 00\nC onLcree Lt,C0T42823-7CP I EMNSYSTO ITCRR OPOACT 00\nAmericanH ospiatlSe rviroceGus pL LC0T42848-4 NICENS AGTERSTEDRI EGNOALITNA 00\n00\nT042851-8 TSYS Merchant Solutions, LLC EMNSYSTO ITCRR OPOACT\n0T42855D-9QCMo niotringSe rviLce Ls,C EMNSYSTO ITCRR OPOACT 00\npOe raitnLLCg ...,0T42856-7BKEP EMNSYSTO ITCRR OPOACT 00\nL LN,CIGTD& ECRN OANIGAIT0T42868P-2BARER BII NICENS AGTERSTEDRI EGNOALITNA\n0T42872NH-4W o ldinLg Ls,C NICENS AGTERSTEDRI EGNOALITNA 8 8\nSo uhLte La,Cst0T42879R-9GEP EMNSYSTO ITCRR OPOACT 00\n0!42886-4R esurgeHn etaMelh& dt icaLl L,C EMNSYSTO ITCRR OPOACT 00\nripulFneB d inLg L,CT0T42890o-6Ga l NIC .ENS,AGTERSTEDRI EGNOALITNA\nripulFneB d inLg2 L ,CT0T42891o-4Ga l NIC .ENS,AGTERSTEDRI EGNOALITNA\nechL LCT0T42892-2Ed ison EMNSYSTO ITCRR OPOACT\nAmeriLca L,Cilteo fT0T42893-0C ommerce NICENS AGTERSTEDRI EGNOALITNA 00\n0T42894-8Emp oweElLr eri Lctc,C EMNSYSTO ITCRR OPOACT 00\n0T42895-5Pah tologSoy luitoLn Ls,C EMNSYSTO ITCRR OPOACT 00\nL L,C0T42896-3CLN OEMANISU RANRUCGOPE NICENS AGTERSTEDRI EGNOALITNA 00\n00\n0T42903-7Pa radigDrom KDGuLLC p ..., EMNSYSTO ITCRR OPOACT\n00\n0T42907-8D esignLinLeU L SA,C NICENS AGTERSTEDRI EGNOALITNA\nL L,C0T42909-4C roslandMa ncheestr EMNSYSTO ITCRR OPOACT 00\n0T42913-6C apiatlExpro reGuLss p L,C EMNSYSTO ITCRR OPOACT 00\n00\n0T429ro1GuL4JM p L-4O,C EMNSYSTO ITCRR OPOACT\n00\nLLC ...ECES,THINLGOOANCLEDSOAR ADV0T42917-7 NICENS AGTERSTEDRI EGNOALITNA\nL L,CENAGCYNISU RANCE 0T42927-6D T EMNSYSTO ITCRR OPOACT 00\n0T42929-2Eve rydreaGeLy n L,C EMNSYSTO ITCRR OPOACT 00\nL L,CRUGOP NIANFCAL I0!42932LPH-6OIAN T EDTNICRRLNS OPOAIIGBUNFSIESS\nechnicalSo luitoLn Ls,CT0T42933l-4Ga cier EMNSYSTO ITCRR OPOACT\n,0T42934-2SmihC t onruistctonL imietdL iabilCiy otmpany EMSNSYSTO ITCRR OPOACT 00",
    "char_count": 2386,
    "word_count": 307,
    "anomalies": {
      "page_number": 2240,
      "source": "MERGED-Kettler",
      "address_clusters": [],
      "entity_variations": [],
      "date_sequences": [],
      "suspicious_patterns": []
    }
  },
  "text_representation": "page_number: 2240 | text: 1310210013\n1310210013\n0T42776-7Ka halaR eastuLLCra ...ns,t EMNSYSTO ITCRR OPOACT 00\n0T42781-7Bro adostneL aurelH ighlanLd Ls,C EMNSYSTO ITCRR OPOACT 00\niaDst esignBu ilLd L,C0T42782-5V EMNSYSTO ITCRR OPOACT 00\nAllianceC ommuniiLte Ls,C0T42784-1 EMNSYSTO ITCRR OPOACT 00\n0T42787-4 RaPoweLr-3 L,C EMNSYSTO ITCRR OPOACT 00\n0T42792h-4Wie tcoR esidenitalMa nageLme Ln,Ct EMNSYSTO ITCRR OPOACT 00\nCLVIES LCSER AMT0T42801-3 NICENS AGTERSTEDRI EGNOALITNA 00\n0T42803kuL-9In L ,C EMNSYSTO ITCRR OPOACT 00\nL LC0T42807-0PRMARSEC OK UYRTI EMNSYSTO ITCRR OPOACT 00\nLL LGEBE,CAX RAIFF 0T42809-6C PT EMNSYSTO ITCRR OPOACT 00\nioctriainFn anLce L,C0T42814-6V EMNSYSTO ITCRR OPOACT 00\nC onLcree Lt,C0T42823-7CP I EMNSYSTO ITCRR OPOACT 00\nAmericanH ospiatlSe rviroceGus pL LC0T42848-4 NICENS AGTERSTEDRI EGNOALITNA 00\n00\nT042851-8 TSYS Merchant Solutions, LLC EMNSYSTO ITCRR OPOACT\n0T42855D-9QCMo niotringSe rviLce Ls,C EMNSYSTO ITCRR OPOACT 00\npOe raitnLLCg ...,0T42856-7BKEP EMNSYSTO ITCRR OPOACT 00\nL LN,CIGTD& ECRN OANIGAIT0T42868P-2BARER BII NICENS AGTERSTEDRI EGNOALITNA\n0T42872NH-4W o ldinLg Ls,C NICENS AGTERSTEDRI EGNOALITNA 8 8\nSo uhLte La,Cst0T42879R-9GEP EMNSYSTO ITCRR OPOACT 00\n0!42886-4R esurgeHn etaMelh& dt icaLl L,C EMNSYSTO ITCRR OPOACT 00\nripulFneB d inLg L,CT0T42890o-6Ga l NIC .ENS,AGTERSTEDRI EGNOALITNA\nripulFneB d inLg2 L ,CT0T42891o-4Ga l NIC .ENS,AGTERSTEDRI EGNOALITNA\nechL LCT0T42892-2Ed ison EMNSYSTO ITCRR OPOACT\nAmeriLca L,Cilteo fT0T42893-0C ommerce NICENS AGTERSTEDRI EGNOALITNA 00\n0T42894-8Emp oweElLr eri Lctc,C EMNSYSTO ITCRR OPOACT 00\n0T42895-5Pah tologSoy luitoLn Ls,C EMNSYSTO ITCRR OPOACT 00\nL L,C0T42896-3CLN OEMANISU RANRUCGOPE NICENS AGTERSTEDRI EGNOALITNA 00\n00\n0T42903-7Pa radigDrom KDGuLLC p ..., EMNSYSTO ITCRR OPOACT\n00\n0T42907-8D esignLinLeU L SA,C NICENS AGTERSTEDRI EGNOALITNA\nL L,C0T42909-4C roslandMa ncheestr EMNSYSTO ITCRR OPOACT 00\n0T42913-6C apiatlExpro reGuLss p L,C EMNSYSTO ITCRR OPOACT 00\n00\n0T429ro1GuL4JM p L-4O,C EMNSYSTO ITCRR OPOACT\n00\nLLC ...ECES,THINLGOOANCLEDSOAR ADV0T42917-7 NICENS AGTERSTEDRI EGNOALITNA\nL L,CENAGCYNISU RANCE 0T42927-6D T EMNSYSTO ITCRR OPOACT 00\n0T42929-2Eve rydreaGeLy n L,C EMNSYSTO ITCRR OPOACT 00\nL L,CRUGOP NIANFCAL I0!42932LPH-6OIAN T EDTNICRRLNS OPOAIIGBUNFSIESS\nechnicalSo luitoLn Ls,CT0T42933l-4Ga cier EMNSYSTO ITCRR OPOACT\n,0T42934-2SmihC t onruistctonL imietdL iabilCiy otmpany EMSNSYSTO ITCRR OPOACT 00 | char_count: 2386 | word_count: 307 | anomalies: {\"page_number\":2240,\"source\":\"MERGED-Kettler\",\"address_clusters\":[],\"entity_variations\":[],\"date_sequences\":[],\"suspicious_patterns\":[]}",
  "embedding": [
    -0.10475236177444458,
    0.02347363717854023,
    -0.02611733414232731,
    -0.10396556556224823,
    0.005113979801535606,
    -0.07559431344270706,
    0.001586311380378902,
    0.03500252962112427,
    0.00304596615023911,
    0.003154973965138197,
    0.09857802838087082,
    -0.0020325088407844305,
    0.03847317397594452,
    -0.019291451200842857,
    -0.15071630477905273,
    -0.03182921186089516,
    -0.03561795502901077,
    -0.0487445630133152,
    -0.022049318999052048,
    -0.04713628441095352,
    0.009934580884873867,
    0.11708395928144455,
    -0.054720617830753326,
    -0.06366712599992752,
    0.011566229164600372,
    0.08505475521087646,
    -0.12565414607524872,
    0.04555191472172737,
    -0.08818300813436508,
    -0.1353863924741745,
    0.03280884400010109,
    0.03475568816065788,
    0.028453627601265907,
    0.03345094993710518,
    0.07456530630588531,
    0.04934142529964447,
    -0.05621543899178505,
    0.00344823463819921,
    0.01894925720989704,
    0.01018287893384695,
    0.02775803953409195,
    -0.05004012584686279,
    0.06402265280485153,
    0.05414996296167374,
    0.02141820266842842,
    0.031078346073627472,
    -0.07354367524385452,
    -0.012858645990490913,
    0.005005006678402424,
    -0.033104315400123596,
    0.049636129289865494,
    0.06425785273313522,
    -0.009245973080396652,
    -0.005861351732164621,
    -0.06763193756341934,
    -0.06576258689165115,
    -0.0813138484954834,
    -0.06453660875558853,
    0.03698335587978363,
    0.00900927186012268,
    0.0637412816286087,
    0.06085841730237007,
    0.015319465659558773,
    -0.015068682841956615,
    1.1210848242626525e-05,
    -0.015058324672281742,
    -0.0061293961480259895,
    -0.04191676154732704,
    -0.036787208169698715,
    -0.01187071017920971,
    -0.006753146648406982,
    0.0420658215880394,
    0.05242002755403519,
    0.07795768976211548,
    0.009043391793966293,
    0.07062854617834091,
    -0.0014757715398445725,
    -0.08073053508996964,
    0.03941396623849869,
    -0.03782735764980316,
    0.007860349491238594,
    0.011490149423480034,
    0.024487538263201714,
    0.06592737138271332,
    0.010295748710632324,
    0.027871528640389442,
    0.020435921847820282,
    -0.02371366135776043,
    0.10143741220235825,
    0.021356286481022835,
    0.04454972594976425,
    0.027830712497234344,
    0.011737825348973274,
    0.024368980899453163,
    -0.017471173778176308,
    0.014744089916348457,
    0.029196375980973244,
    0.030154084786772728,
    -0.1482061892747879,
    0.06273354589939117,
    -0.021552428603172302,
    -0.036825817078351974,
    -0.014333787374198437,
    -0.06437747180461884,
    -0.0624115914106369,
    -0.037146031856536865,
    0.05556197464466095,
    0.024419942870736122,
    0.03354469686746597,
    -0.06808433681726456,
    -0.04229363054037094,
    0.01380091067403555,
    -0.018216324970126152,
    -0.0738392323255539,
    -0.02178674191236496,
    -0.0397002138197422,
    -0.00608022790402174,
    -0.03980870917439461,
    0.058104511350393295,
    -0.022698748856782913,
    0.005138739477843046,
    -0.05646013468503952,
    -0.07467800378799438,
    0.018031127750873566,
    -0.039334844797849655,
    -0.00724969245493412,
    0.03879382833838463,
    2.4365986327838175e-32,
    -0.0007680539856664836,
    0.015370763838291168,
    0.018438387662172318,
    0.025394219905138016,
    0.008693930692970753,
    -0.007637032773345709,
    -0.04807461053133011,
    0.01618952490389347,
    -0.05666917562484741,
    0.037483856081962585,
    -0.1084761843085289,
    -0.07185765355825424,
    0.02713649533689022,
    -0.005830302368849516,
    0.02449568174779415,
    -0.07297857105731964,
    0.08895383775234222,
    -0.034478433430194855,
    -0.09122467041015625,
    -0.04926631972193718,
    0.03842759132385254,
    0.001065786462277174,
    -0.035130616277456284,
    -0.05264529585838318,
    0.02740403637290001,
    0.08152423053979874,
    -0.05967229977250099,
    -0.08588501065969467,
    0.03063381090760231,
    0.012492655776441097,
    0.03779098019003868,
    0.04720054194331169,
    -0.04188162460923195,
    0.023900620639324188,
    0.0012613196158781648,
    0.008497987873852253,
    0.024422191083431244,
    -0.08696049451828003,
    -0.0132853202521801,
    -0.014624005183577538,
    0.0041380939073860645,
    0.05313863605260849,
    -0.047196295112371445,
    0.012606465257704258,
    0.07600021362304688,
    -0.028348440304398537,
    -0.013540501706302166,
    0.011169765144586563,
    0.001605904195457697,
    0.019257739186286926,
    -0.009636074304580688,
    0.01681009866297245,
    -0.011037368327379227,
    0.03664315119385719,
    -0.012955416925251484,
    -0.005809464957565069,
    -0.02417227439582348,
    0.045412320643663406,
    0.06968594342470169,
    0.06619268655776978,
    0.002554333535954356,
    -0.0021065056789666414,
    -0.0003690938465297222,
    -0.06709568947553635,
    0.06959040462970734,
    -0.0636032298207283,
    -0.008153092116117477,
    -0.035441283136606216,
    -0.04048054292798042,
    -0.010825247503817081,
    -0.007505979388952255,
    -0.08140186965465546,
    0.07933657616376877,
    0.03503698855638504,
    -0.032051246613264084,
    0.009230655618011951,
    -0.01875106617808342,
    0.06761012971401215,
    -0.0643090009689331,
    -0.06749945133924484,
    -0.027581539005041122,
    -0.031829070299863815,
    -0.024852635338902473,
    -0.05411626398563385,
    0.031212259083986282,
    -0.018535111099481583,
    -0.016214601695537567,
    -0.0815272256731987,
    -0.002832996193319559,
    0.05223378166556358,
    0.007668264210224152,
    0.007615163456648588,
    -0.0544707328081131,
    -0.0028943491633981466,
    -0.0847809836268425,
    -2.3410137504570848e-32,
    -0.05728919804096222,
    -0.03343615308403969,
    -0.039081871509552,
    -0.002251899568364024,
    -0.04993977025151253,
    -0.01979086548089981,
    -0.015276568941771984,
    0.0953337773680687,
    0.04578573629260063,
    0.05963820219039917,
    0.03513273224234581,
    0.0322018601000309,
    0.03708776831626892,
    -0.1218944564461708,
    0.10051219165325165,
    0.05163275822997093,
    0.0049677202478051186,
    0.046391624957323074,
    -0.013200362212955952,
    0.08702801167964935,
    -0.05123872682452202,
    0.1150604784488678,
    -0.03908046707510948,
    0.01981900818645954,
    0.020904581993818283,
    0.08031149953603745,
    0.02406397834420204,
    0.04425271227955818,
    0.03416389971971512,
    -0.010156176052987576,
    0.010425620712339878,
    -0.037047069519758224,
    -0.06038809195160866,
    0.14220649003982544,
    -0.05775858834385872,
    0.011339091695845127,
    0.06735214591026306,
    -0.013238983228802681,
    -0.030945245176553726,
    0.014387605711817741,
    0.0898568332195282,
    -0.0060033337213099,
    -0.0148348743095994,
    0.053277064114809036,
    -0.052820269018411636,
    -0.007581930607557297,
    0.04944858327507973,
    0.016674330458045006,
    0.011522389948368073,
    -0.0074794418178498745,
    0.13393321633338928,
    -0.04504789412021637,
    0.00561091722920537,
    0.06726039946079254,
    0.04964667931199074,
    0.02035447582602501,
    0.020239615812897682,
    -0.03989892825484276,
    -0.122656911611557,
    -0.099577397108078,
    0.10604012757539749,
    -0.015967881307005882,
    -0.0434289276599884,
    0.025251049548387527,
    0.09688377380371094,
    -0.04396495595574379,
    -0.03516215831041336,
    0.01563812606036663,
    0.009287381544709206,
    -0.06842248886823654,
    0.02153395302593708,
    -0.030145490542054176,
    -0.10524828732013702,
    -0.10397253185510635,
    0.12750384211540222,
    -0.02052069827914238,
    -0.04924588277935982,
    -0.04200023040175438,
    -0.10750095546245575,
    -0.017303824424743652,
    -0.059326525777578354,
    -0.02772752195596695,
    0.02604403905570507,
    -0.03157860413193703,
    0.019364681094884872,
    -0.030913475900888443,
    0.06605455279350281,
    0.06990312784910202,
    -0.00863383337855339,
    -0.0272781141102314,
    -0.03058491460978985,
    -0.0028836922720074654,
    0.0032853600569069386,
    0.12515780329704285,
    -0.007471091113984585,
    -7.270811863691051e-08,
    0.016196055337786674,
    0.018550483509898186,
    -0.002697594230994582,
    -0.003518823767080903,
    0.005476247984915972,
    -0.02193480357527733,
    0.08957816660404205,
    0.02383984811604023,
    -0.04104948788881302,
    -0.025376800447702408,
    0.015157325193285942,
    -0.027395740151405334,
    -0.011889530345797539,
    -0.07407388836145401,
    0.0956382006406784,
    -0.040659159421920776,
    -0.05047575384378433,
    0.024688411504030228,
    -0.05652342736721039,
    -0.045078348368406296,
    -0.032477159053087234,
    -0.030855152755975723,
    -0.020260585471987724,
    -0.060196176171302795,
    -0.010735917836427689,
    0.01813347078859806,
    0.045548371970653534,
    0.028554163873195648,
    -0.011491394601762295,
    0.021929830312728882,
    -0.01842760667204857,
    -0.03709448128938675,
    0.006767038721591234,
    -0.07039477676153183,
    -0.023326532915234566,
    0.0760950893163681,
    -0.017895998433232307,
    -0.05058146268129349,
    0.05097874999046326,
    -0.04036673903465271,
    -0.04096011444926262,
    0.0333896242082119,
    -0.014791341498494148,
    0.07186371833086014,
    -0.01794140599668026,
    0.0236130952835083,
    -0.006849084980785847,
    -0.025804124772548676,
    0.1130453497171402,
    -0.15241923928260803,
    -0.009866305626928806,
    -0.0008141312282532454,
    0.03297077491879463,
    0.005416473373770714,
    -0.07993434369564056,
    -0.05777134373784065,
    0.03002866730093956,
    -0.0053475843742489815,
    0.08772295713424683,
    0.06535504013299942,
    0.056697797030210495,
    -0.06938830018043518,
    -0.024725740775465965,
    -0.04441997781395912
  ]
}