{
  "metadata": {
    "source": "pdf_analysis",
    "created": "2025-12-11T00:54:15.180058",
    "file_path": "/Users/machine/Documents/kettler-data-analysis/research/texas/pdf_analysis/MERGED-Kettler/pages/page_0515.json",
    "has_embedding": true
  },
  "data": {
    "page_number": 515,
    "text": "1310210013\n1310210913\n0738970-3 Damodaran Foundation, Inc., The EDTNICRRLNS OPOAIIGBUNFSIESS 00\n0739070-1Mo dernSo ldniIc.ePo r e,t NICENS AGTERSTEDRI EGNOALITNA 01\nAssociaitoPano rceMo flB sa ic0739126-1Uw nOni etrs EMNSYSTO ITCRR OPOACT 00\n0739127-9D upoCn rentaiIc.tve , EDTNICRRLNS OPOAIIGBUNFSIESS 00\nNICAX .RAIFF FNOO ITC REA0739133-71 L NIC .ENS,AGTERSTEDRI EGNOALITNA 00\nirginniIc.a ,0739174-1Xi neVrgo y f EMNSYSTO ITCRR OPOACT 00\nraockeFur ndaitonnIc. T0739232-7Se izure EDTNICRRLNS OPOAIIGBUNFSIESS 00\neKnnSPE on xviIc.l l,eI TApple 0739452-1 EMNSYSTO ITCRR OPOACT 00\nenSe rviceKns onxviIc.l l,eI TApple 0739453-9 EMNSYSTO ITCRR OPOACT 00\nHneOaIc.nSPE re ,TApple 0739522-1 EMNSYSTO ITCRR OPOACT 00\nenSe rviHnceOaIc.s re ,TApple 0739523-9 EMNSYSTO ITCRR OPOACT 00\n0739668-2C ou-CoOthk arleotsvitlnlIc.e , EMNSYSTO ITCRR OPOACT 00\n0739768-0 FC Sports, Inc. EDTNICRRLNS OPOAIIGBUNFSIESS 00\n0739882-9 SAABLABS Inc. EDTNICRRLNS OPOAIIGBUNFSIESS 00\n0740060-9 T & L’S LAND WORKS, INC. NICENS AGTERSTEDRI EGNOALITNA 00\nnIc. AAdveirtsingR esourceVs 0740151-6 EMNSYSTO ITCRR OPOACT 00\n0740264-7C lounedItl ligeSon ltuintoIc.n s, NICENS AGTERSTEDRI EGNOALITNA\nNIC .TRTANRSPOS Y’0740302-5KEL L EDTNICRRLNS OPOAIIGBUNFSIESS\nAlexandriaJa yceoeFus ndaiton0740503-8 EMNSYSTO ITCRR OPOACT\nHnAtoaIc.wFrm 0740580-6 EDTNICRRLNS OPOAIIGBUNFSIESS\nAlaCf ommunicaitonnIc.s 0740685-3 NICENS AGTERSTEDRI EGNOALITNA 01\n0740879-2Sh enandoahC onncreeIc.t EMNSYSTO ITCRR OPOACT\noiceH anlIc.l ,0741002l-0Go balV EMNSYSTO ITCRR OPOACT 00\nosfrtAdvocaeRt esponsibleEf AmericahnWos 0741004-6 EMNSYSTO ITCRR OPOACT\n.NCROS OPIT0741081-4CCMMU VM ONCIA EDTNICRRLNS OPOAIIGBUNFSIESS 00\nynchbnuIc.rg ,0741098-8C ou-LoOtk EMNSYSTO ITCRR OPOACT\n0741351-1C oePemmiteo rpt feutaulGa rdians EMNSYSTO ITCRR OPOACT 00\n0741451-9Jui stceC oalSa leCs orporaiton EMNSYSTO ITCRR OPOACT 00\nAssociaiton0741588-8D ooPaictr teMen dtical EMNSYSTO ITCRR OPOACT 00\nAlliance0741590-4Pai tePon wter EMNSYSTO ITCRR OPOACT 00\nsdeScotannSPE tlIc. e ,TApple 0741685-2 EMNSYSTO ITCRR OPOACT 00\nenSe rvisdceScotans tlIc.e ,TApple 0741686-0 EMNSYSTO ITCRR OPOACT 00\nexaSens rviIc.ce s,TenH ospiatliy tTApple 0741687-8 EMNSYSTO ITCRR OPOACT\nAdneIc.pi ts,0742420-3 EDTNICRRLNS OPOAIIGBUNFSIESS 00\nAppleEiC gSPE hh atrleotsvitlnlIc.e ,0742551-5 C T CORPORATION SYSTEM 00\nirginiaBe anchNIc. oh rt,AppleEiV gSPE h t0742552-3 CT CORPORATION SYSTEM 00\nirginiaBe anchSoIc. uh t,AppleEiV gSPE h t0742553-1 C T CORPORATION SYSTEM 00\nnIc. ,AppleEi gCh atrolinaBe aPchG 0742554-9 C T CORPORATION SYSTEM 00",
    "char_count": 2535,
    "word_count": 314,
    "anomalies": {
      "page_number": 515,
      "source": "MERGED-Kettler",
      "address_clusters": [],
      "entity_variations": [],
      "date_sequences": [],
      "suspicious_patterns": []
    }
  },
  "text_representation": "page_number: 515 | text: 1310210013\n1310210913\n0738970-3 Damodaran Foundation, Inc., The EDTNICRRLNS OPOAIIGBUNFSIESS 00\n0739070-1Mo dernSo ldniIc.ePo r e,t NICENS AGTERSTEDRI EGNOALITNA 01\nAssociaitoPano rceMo flB sa ic0739126-1Uw nOni etrs EMNSYSTO ITCRR OPOACT 00\n0739127-9D upoCn rentaiIc.tve , EDTNICRRLNS OPOAIIGBUNFSIESS 00\nNICAX .RAIFF FNOO ITC REA0739133-71 L NIC .ENS,AGTERSTEDRI EGNOALITNA 00\nirginniIc.a ,0739174-1Xi neVrgo y f EMNSYSTO ITCRR OPOACT 00\nraockeFur ndaitonnIc. T0739232-7Se izure EDTNICRRLNS OPOAIIGBUNFSIESS 00\neKnnSPE on xviIc.l l,eI TApple 0739452-1 EMNSYSTO ITCRR OPOACT 00\nenSe rviceKns onxviIc.l l,eI TApple 0739453-9 EMNSYSTO ITCRR OPOACT 00\nHneOaIc.nSPE re ,TApple 0739522-1 EMNSYSTO ITCRR OPOACT 00\nenSe rviHnceOaIc.s re ,TApple 0739523-9 EMNSYSTO ITCRR OPOACT 00\n0739668-2C ou-CoOthk arleotsvitlnlIc.e , EMNSYSTO ITCRR OPOACT 00\n0739768-0 FC Sports, Inc. EDTNICRRLNS OPOAIIGBUNFSIESS 00\n0739882-9 SAABLABS Inc. EDTNICRRLNS OPOAIIGBUNFSIESS 00\n0740060-9 T & L’S LAND WORKS, INC. NICENS AGTERSTEDRI EGNOALITNA 00\nnIc. AAdveirtsingR esourceVs 0740151-6 EMNSYSTO ITCRR OPOACT 00\n0740264-7C lounedItl ligeSon ltuintoIc.n s, NICENS AGTERSTEDRI EGNOALITNA\nNIC .TRTANRSPOS Y’0740302-5KEL L EDTNICRRLNS OPOAIIGBUNFSIESS\nAlexandriaJa yceoeFus ndaiton0740503-8 EMNSYSTO ITCRR OPOACT\nHnAtoaIc.wFrm 0740580-6 EDTNICRRLNS OPOAIIGBUNFSIESS\nAlaCf ommunicaitonnIc.s 0740685-3 NICENS AGTERSTEDRI EGNOALITNA 01\n0740879-2Sh enandoahC onncreeIc.t EMNSYSTO ITCRR OPOACT\noiceH anlIc.l ,0741002l-0Go balV EMNSYSTO ITCRR OPOACT 00\nosfrtAdvocaeRt esponsibleEf AmericahnWos 0741004-6 EMNSYSTO ITCRR OPOACT\n.NCROS OPIT0741081-4CCMMU VM ONCIA EDTNICRRLNS OPOAIIGBUNFSIESS 00\nynchbnuIc.rg ,0741098-8C ou-LoOtk EMNSYSTO ITCRR OPOACT\n0741351-1C oePemmiteo rpt feutaulGa rdians EMNSYSTO ITCRR OPOACT 00\n0741451-9Jui stceC oalSa leCs orporaiton EMNSYSTO ITCRR OPOACT 00\nAssociaiton0741588-8D ooPaictr teMen dtical EMNSYSTO ITCRR OPOACT 00\nAlliance0741590-4Pai tePon wter EMNSYSTO ITCRR OPOACT 00\nsdeScotannSPE tlIc. e ,TApple 0741685-2 EMNSYSTO ITCRR OPOACT 00\nenSe rvisdceScotans tlIc.e ,TApple 0741686-0 EMNSYSTO ITCRR OPOACT 00\nexaSens rviIc.ce s,TenH ospiatliy tTApple 0741687-8 EMNSYSTO ITCRR OPOACT\nAdneIc.pi ts,0742420-3 EDTNICRRLNS OPOAIIGBUNFSIESS 00\nAppleEiC gSPE hh atrleotsvitlnlIc.e ,0742551-5 C T CORPORATION SYSTEM 00\nirginiaBe anchNIc. oh rt,AppleEiV gSPE h t0742552-3 CT CORPORATION SYSTEM 00\nirginiaBe anchSoIc. uh t,AppleEiV gSPE h t0742553-1 C T CORPORATION SYSTEM 00\nnIc. ,AppleEi gCh atrolinaBe aPchG 0742554-9 C T CORPORATION SYSTEM 00 | char_count: 2535 | word_count: 314 | anomalies: {\"page_number\":515,\"source\":\"MERGED-Kettler\",\"address_clusters\":[],\"entity_variations\":[],\"date_sequences\":[],\"suspicious_patterns\":[]}",
  "embedding": [
    -0.09265100210905075,
    -0.015359096229076385,
    -0.03055291622877121,
    -0.04163617268204689,
    0.045656971633434296,
    -0.06900253146886826,
    0.028439410030841827,
    0.08798768371343613,
    -0.0064161308109760284,
    0.015317598357796669,
    0.07164115458726883,
    -0.010023918002843857,
    -0.007020849734544754,
    -0.011664802208542824,
    -0.16515274345874786,
    -0.07262533903121948,
    -0.021892007440328598,
    -0.035139020532369614,
    -0.012756607495248318,
    -0.0051396917551755905,
    0.01778978668153286,
    0.131461039185524,
    -0.01777125522494316,
    -0.04126214608550072,
    -0.0034258312080055475,
    0.04737480729818344,
    -0.08899597823619843,
    0.027247019112110138,
    -0.08665639162063599,
    -0.13646620512008667,
    0.05745159834623337,
    0.07005155086517334,
    0.06711477786302567,
    -0.01985696330666542,
    0.06686731427907944,
    0.045850638300180435,
    -0.039754390716552734,
    -0.021331680938601494,
    0.03437409922480583,
    0.013315470889210701,
    0.029880093410611153,
    -0.04800175502896309,
    0.05566316097974777,
    0.027383137494325638,
    -0.010949869640171528,
    -0.012113071046769619,
    -0.049279697239398956,
    -0.0312979556620121,
    0.0023282046895474195,
    -0.012861481867730618,
    0.033050745725631714,
    0.045133326202631,
    0.03094395622611046,
    0.01581956259906292,
    -0.032068148255348206,
    -0.09520316869020462,
    -0.038569848984479904,
    -0.05895443633198738,
    0.0138583704829216,
    0.020304031670093536,
    0.08880023658275604,
    0.026647718623280525,
    -0.006753053981810808,
    -0.024161402136087418,
    0.03569171950221062,
    0.0037130548153072596,
    -0.012610074132680893,
    -0.04475848749279976,
    -0.03728492558002472,
    -0.031190354377031326,
    -0.002208803780376911,
    0.03830699995160103,
    0.027590665966272354,
    0.10472925007343292,
    0.018994584679603577,
    0.10862904787063599,
    0.013185344636440277,
    -0.02607010491192341,
    0.09369868785142899,
    -0.04075750708580017,
    -0.02041815035045147,
    0.031594060361385345,
    0.05101531744003296,
    0.018953830003738403,
    -0.004193540196865797,
    0.02774859592318535,
    0.040530815720558167,
    -0.006569423247128725,
    0.10002651065587997,
    0.009473064914345741,
    0.08497174829244614,
    0.07013960182666779,
    0.0025383494794368744,
    0.02605821192264557,
    -0.033090874552726746,
    0.0038823119830340147,
    0.000683708640281111,
    0.009354409761726856,
    -0.1044950932264328,
    0.05483187735080719,
    -0.024332035332918167,
    -0.024908192455768585,
    -0.05319802090525627,
    -0.0538603812456131,
    -0.13114355504512787,
    -0.052020445466041565,
    0.008425855077803135,
    0.001957216300070286,
    0.042498208582401276,
    -0.037365712225437164,
    -0.08055823296308517,
    -0.05051957815885544,
    -0.003249144647270441,
    -0.05489642545580864,
    -0.02267461083829403,
    -0.04684295132756233,
    -0.013874419964849949,
    -0.04210595414042473,
    0.051855672150850296,
    -0.051131270825862885,
    0.01186054665595293,
    -0.04820257052779198,
    -0.06946098059415817,
    0.017147209495306015,
    -0.03541342169046402,
    -0.04534347355365753,
    0.003528685076162219,
    3.322500399389434e-32,
    0.005272747483104467,
    0.0023960007820278406,
    -0.01330583542585373,
    0.003582666628062725,
    0.03159496933221817,
    -0.031763751059770584,
    -0.07018522173166275,
    -0.0012066325871273875,
    -0.041621651500463486,
    0.016089100390672684,
    -0.09170260280370712,
    -0.042351141571998596,
    0.027780350297689438,
    -0.025301139801740646,
    -0.016422362998127937,
    -0.050174273550510406,
    0.08304799348115921,
    -0.02035038359463215,
    -0.06907351315021515,
    -0.016434136778116226,
    0.035127248615026474,
    -0.01762222684919834,
    -0.02682497724890709,
    -0.067935049533844,
    5.734999285778031e-05,
    0.0679263025522232,
    -0.06507373601198196,
    -0.07184692472219467,
    0.04129260778427124,
    0.029432669281959534,
    0.04627136141061783,
    -0.035615500062704086,
    -0.04033293575048447,
    0.02029149793088436,
    0.03194073587656021,
    -0.016589820384979248,
    0.03470923379063606,
    -0.04761366918683052,
    -0.059975240379571915,
    -0.03418070450425148,
    0.03003728948533535,
    0.08025404065847397,
    -0.038599077612161636,
    0.05667613074183464,
    0.10550130903720856,
    -0.012121584266424179,
    0.03160969167947769,
    0.018055004999041557,
    0.020912127569317818,
    0.03381671756505966,
    -0.02735884115099907,
    0.020460840314626694,
    -0.01642204076051712,
    0.008280273526906967,
    -0.0005858455551788211,
    -0.01691071130335331,
    -0.04103212058544159,
    0.017665036022663116,
    0.09844408184289932,
    -0.01775030978024006,
    0.009830182418227196,
    0.04094194620847702,
    0.00015683491074014455,
    -0.10503478348255157,
    0.06426035612821579,
    -0.04452146962285042,
    -0.012198748998343945,
    -0.009384921751916409,
    0.0004659445257857442,
    -0.03421669453382492,
    -0.006909422110766172,
    -0.06254786998033524,
    0.0746520459651947,
    0.07116305828094482,
    -0.05289135500788689,
    -0.010715669952332973,
    0.0010727967601269484,
    0.05702444538474083,
    -0.03863554447889328,
    -0.024525200948119164,
    -0.04345961660146713,
    -0.02955535054206848,
    -0.03156852349638939,
    -0.04358188435435295,
    -0.021702108904719353,
    -0.0006261779926717281,
    -0.03432841598987579,
    -0.0317869670689106,
    -0.027825744822621346,
    0.030768994241952896,
    0.06844250857830048,
    0.0038995787035673857,
    -0.05723794922232628,
    0.013545582070946693,
    -0.05873763933777809,
    -3.036743894049878e-32,
    0.008821633644402027,
    -0.05631294101476669,
    -0.0447782501578331,
    -0.025610772892832756,
    -0.03804730623960495,
    -0.015004497952759266,
    -0.05068694427609444,
    0.09012778848409653,
    0.09611086547374725,
    -0.021532952785491943,
    0.050690386444330215,
    0.007597325369715691,
    0.025815023109316826,
    -0.1338183581829071,
    0.06658484786748886,
    0.03179612010717392,
    -0.0038375058211386204,
    0.04573853313922882,
    -0.03513823822140694,
    0.04882374405860901,
    -0.02894807979464531,
    0.08180902153253555,
    -0.05985736474394798,
    0.022654855623841286,
    -0.03239981085062027,
    0.13201852142810822,
    0.009983766824007034,
    0.03911194950342178,
    -0.00570561783388257,
    0.012200376950204372,
    -0.006208259146660566,
    -0.026038408279418945,
    -0.11549422889947891,
    0.13661636412143707,
    -0.09139014780521393,
    -0.007262208499014378,
    0.07898863404989243,
    -0.04989790543913841,
    -0.07929070293903351,
    0.02622270956635475,
    0.10086681693792343,
    0.07348274439573288,
    0.0022093511652201414,
    0.032232824712991714,
    -0.025924354791641235,
    -0.014907795004546642,
    0.012995654717087746,
    0.015723565593361855,
    0.054225217550992966,
    -0.008090407587587833,
    0.1259250044822693,
    0.028051935136318207,
    -0.02861865609884262,
    0.040963057428598404,
    0.08645011484622955,
    0.012531363405287266,
    0.049685120582580566,
    -0.02924959361553192,
    -0.11698766052722931,
    -0.04456930235028267,
    0.10647377371788025,
    -0.0005530734197236598,
    -0.0423828661441803,
    0.03897054120898247,
    0.07640174776315689,
    0.0042762476950883865,
    -0.05312220752239227,
    0.021982084959745407,
    0.06381510198116302,
    -0.07815219461917877,
    0.05431394651532173,
    -0.0640694797039032,
    -0.10200970619916916,
    -0.10690829902887344,
    0.09145466983318329,
    -0.016076629981398582,
    -0.014383498579263687,
    0.0036346621345728636,
    -0.06688474863767624,
    0.046017128974199295,
    -0.02259628102183342,
    -0.02322417125105858,
    0.0005256471340544522,
    0.042294327169656754,
    0.052156127989292145,
    -0.0518423356115818,
    0.0083114393055439,
    0.0003368072211742401,
    0.003627144731581211,
    -0.01681012474000454,
    -0.01858900859951973,
    -0.0007963492535054684,
    0.00665802787989378,
    0.12364514917135239,
    0.0557730495929718,
    -9.420892155276306e-08,
    0.013277869671583176,
    -0.0427175872027874,
    -0.0024459052365273237,
    -0.0363735556602478,
    0.027416253462433815,
    -0.04489203169941902,
    0.08039769530296326,
    0.010026423260569572,
    -0.05340991169214249,
    -0.05896957963705063,
    0.03262774273753166,
    0.013658336363732815,
    -0.04700235277414322,
    -0.030947234481573105,
    0.10002394765615463,
    -0.08485782891511917,
    -0.006026910152286291,
    0.07059712707996368,
    -0.08675135672092438,
    -0.03105148859322071,
    -0.02394198253750801,
    -0.06388505548238754,
    -0.011167234741151333,
    -0.08743234723806381,
    -0.021853841841220856,
    -0.01716834492981434,
    0.05338349565863609,
    0.013832428492605686,
    -0.027488380670547485,
    0.01486395113170147,
    -0.033201590180397034,
    -0.03135964274406433,
    -0.0016583927208557725,
    -0.08734872937202454,
    -0.0029361306224018335,
    0.08886659890413284,
    -0.010342729277908802,
    -0.01984754577279091,
    0.013230050913989544,
    -0.01970154605805874,
    -0.04467381536960602,
    0.03081955574452877,
    -0.019968152046203613,
    0.0441683828830719,
    0.008508415892720222,
    0.009621227160096169,
    -0.007969184778630733,
    0.0005954300286248326,
    0.08613366633653641,
    -0.17112509906291962,
    -0.006753255613148212,
    0.008001098409295082,
    0.008735905401408672,
    -0.009653681889176369,
    -0.09417545795440674,
    -0.05358339846134186,
    -0.010238041169941425,
    0.02491905353963375,
    0.03288952261209488,
    0.030147820711135864,
    0.06664957851171494,
    -0.09580651670694351,
    0.014763708226382732,
    -0.0337364636361599
  ]
}