{
  "metadata": {
    "source": "pdf_analysis",
    "created": "2025-12-11T00:36:10.026476",
    "file_path": "/Users/machine/Documents/kettler-data-analysis/research/texas/pdf_analysis/MERGED-Kettler/pages/page_0629.json",
    "has_embedding": true
  },
  "data": {
    "page_number": 629,
    "text": "1310210013\n1310210013\nHMEMBERLT LCNNRW OOTS407261-95L 0NOD0MADSO I CT CORPORATION SYSTEM 00\n00\nS407702-2Ba nkeSchLr/mi Ld,Ct CT CORPORATION SYSTEM\nS407740o-2Gl dPen aInk ovaitoLn Ls,C NICLNS IIGBUNFSIESS 00\nechniLcs LCTa nArtd S407822-8 EDTNICRRLNS OPOAIIGBUNFSIESS 00\nS407865-7 MezgteLr LC EDTNICRRLNS OPOAIIGBUNFSIESS 00\nS408245e-1Gn eraitonPro peirteLs LC NIC .ENS,AGTERSTEDRI EGNOALITNA 00\nS408394-7 oGodruGbbiLn L’C NIC .ENS,AGTERSTEDRI EGNOALITNA 00\nL L,CS408461-4Ph ysicalSe curiyt EMNSYSTO ITCRR OPOATC 00\nS408649-4 LL ie L.f,CW.OB. EDTNICRRLNS OPOAIIGBUNFSIESS 00\nL LAm,CS408671-8Ke nNaePat n EDTNICRRLNS OPOAIIGBUNFSIESS 00\nS40867R8i i-3FtgKi h dShts oeLs LC EDTNICRRLNS OPOAIIGBUNFSIESS 00\nPL C,S408879-7C onsumeLr aw EDTNICRRLNS OPOAIIGBUNFSIESS 00\nirginiaSp inLe L,CS408924-1V NICENS .AGTERSTEDRI EGNOALITNA 00\nS409167-6 M-HMIaydewnOe nDs riLve L,C EMNSYSTO ITCRR OPOACT 00\n00\nL LES,CIEGTS4095R1STA6 -4CMKO I EMNSYSTO ITCRR OPOACT\nechnologieLs LCTS409556-0C larisys EDTNICRRLNS OPOAIIGBUNFSIESS 00\nAssocilLLCaeIl ...ts ,S409690-7D amuht EMNSYSTO ITCRR OPOACT\nS409767o-3Zo mphL LC NIC .ENS,AGTERSTEDRI EGNOALITNA\nS409926-5 HeraaL C EMNSYSTO ITCRR OPOATC\nS409963-8 MiligLaC Ln& o,C . NIC .ENS,AGTERSTEDRI EGNOALITNA\nS409991-9 PHYS101L LC NIC .ENS,AGTERSTEDRI EGNOALITNA\nS410091-5 HNM oeWtlMa nageLme Ln,Ct EMNSYSTO ITCRR OPOACT\nS410766-2 raiLl L,CTPawohs nte EMNSYSTO ITCRR OPOACT\nS410970-0 oodbridgePh ysicianSe rviLce Ls,CW EMNSYSTO ITCRR OPOATC\nirginiuaQa lCiy atrePanL rte Lrs,C128-4V 1S41 EMNSYSTO ITCRR OPOACT\n166i-4Fl ProR enaIvemeLly stns LttC1S41 EDTNICRRLNS OPOAIIGBUNFSIESS\nAlliedC onsulitnLg L,C1235rae-7Sttg ic S41 EMNSYSTO ITCRR OPOATC\n1240-7S41 Rabona LLC EMNSYSTO ITCRR OPOATC\n1241-5S41 LL LAI,CNROE ETBAC2M 007-4LMEST I EMNSYSTO ITCRR OPOACT\n1522-8S41 PlanaeB2Lt B LC NICLNS IIGBUNFSIESS\n1606-9S41 eFderalC oronGuSEPS pL LC NICLNS IIGBUNFSIESS\n1714-1S41 eSok luitoLn Ls,CTDynamic EDTNICRRLNS OPOAIIGBUNFSIESS\n1876-8S41 SalvoFaLry vo Lrs,C NIC .ENS,AGTERSTEDRI EGNOALITNA\n1914-7S41 HM Investments LLC EMNSYSTO ITCRR OPOACT\nS411917-0 HM Investments I| LLC EMNSYSTO ITCRR OPOACT\nS412047-5 Smart Solutions LLC NIC .ENS,AGTERSTEDRI EGNOALITNA\nS412096-2 CSMC 2007-C1 RETAIL 3601, LLC EMNSYSTO ITCRR OPOACT\nS412232-3 StreamCo East Collins, LLC NIC .ENS,AGTERSTEDRI EGNOALITNA",
    "char_count": 2296,
    "word_count": 282,
    "anomalies": {
      "page_number": 629,
      "source": "MERGED-Kettler",
      "address_clusters": [],
      "entity_variations": [],
      "date_sequences": [],
      "suspicious_patterns": []
    }
  },
  "text_representation": "page_number: 629 | text: 1310210013\n1310210013\nHMEMBERLT LCNNRW OOTS407261-95L 0NOD0MADSO I CT CORPORATION SYSTEM 00\n00\nS407702-2Ba nkeSchLr/mi Ld,Ct CT CORPORATION SYSTEM\nS407740o-2Gl dPen aInk ovaitoLn Ls,C NICLNS IIGBUNFSIESS 00\nechniLcs LCTa nArtd S407822-8 EDTNICRRLNS OPOAIIGBUNFSIESS 00\nS407865-7 MezgteLr LC EDTNICRRLNS OPOAIIGBUNFSIESS 00\nS408245e-1Gn eraitonPro peirteLs LC NIC .ENS,AGTERSTEDRI EGNOALITNA 00\nS408394-7 oGodruGbbiLn L’C NIC .ENS,AGTERSTEDRI EGNOALITNA 00\nL L,CS408461-4Ph ysicalSe curiyt EMNSYSTO ITCRR OPOATC 00\nS408649-4 LL ie L.f,CW.OB. EDTNICRRLNS OPOAIIGBUNFSIESS 00\nL LAm,CS408671-8Ke nNaePat n EDTNICRRLNS OPOAIIGBUNFSIESS 00\nS40867R8i i-3FtgKi h dShts oeLs LC EDTNICRRLNS OPOAIIGBUNFSIESS 00\nPL C,S408879-7C onsumeLr aw EDTNICRRLNS OPOAIIGBUNFSIESS 00\nirginiaSp inLe L,CS408924-1V NICENS .AGTERSTEDRI EGNOALITNA 00\nS409167-6 M-HMIaydewnOe nDs riLve L,C EMNSYSTO ITCRR OPOACT 00\n00\nL LES,CIEGTS4095R1STA6 -4CMKO I EMNSYSTO ITCRR OPOACT\nechnologieLs LCTS409556-0C larisys EDTNICRRLNS OPOAIIGBUNFSIESS 00\nAssocilLLCaeIl ...ts ,S409690-7D amuht EMNSYSTO ITCRR OPOACT\nS409767o-3Zo mphL LC NIC .ENS,AGTERSTEDRI EGNOALITNA\nS409926-5 HeraaL C EMNSYSTO ITCRR OPOATC\nS409963-8 MiligLaC Ln& o,C . NIC .ENS,AGTERSTEDRI EGNOALITNA\nS409991-9 PHYS101L LC NIC .ENS,AGTERSTEDRI EGNOALITNA\nS410091-5 HNM oeWtlMa nageLme Ln,Ct EMNSYSTO ITCRR OPOACT\nS410766-2 raiLl L,CTPawohs nte EMNSYSTO ITCRR OPOACT\nS410970-0 oodbridgePh ysicianSe rviLce Ls,CW EMNSYSTO ITCRR OPOATC\nirginiuaQa lCiy atrePanL rte Lrs,C128-4V 1S41 EMNSYSTO ITCRR OPOACT\n166i-4Fl ProR enaIvemeLly stns LttC1S41 EDTNICRRLNS OPOAIIGBUNFSIESS\nAlliedC onsulitnLg L,C1235rae-7Sttg ic S41 EMNSYSTO ITCRR OPOATC\n1240-7S41 Rabona LLC EMNSYSTO ITCRR OPOATC\n1241-5S41 LL LAI,CNROE ETBAC2M 007-4LMEST I EMNSYSTO ITCRR OPOACT\n1522-8S41 PlanaeB2Lt B LC NICLNS IIGBUNFSIESS\n1606-9S41 eFderalC oronGuSEPS pL LC NICLNS IIGBUNFSIESS\n1714-1S41 eSok luitoLn Ls,CTDynamic EDTNICRRLNS OPOAIIGBUNFSIESS\n1876-8S41 SalvoFaLry vo Lrs,C NIC .ENS,AGTERSTEDRI EGNOALITNA\n1914-7S41 HM Investments LLC EMNSYSTO ITCRR OPOACT\nS411917-0 HM Investments I| LLC EMNSYSTO ITCRR OPOACT\nS412047-5 Smart Solutions LLC NIC .ENS,AGTERSTEDRI EGNOALITNA\nS412096-2 CSMC 2007-C1 RETAIL 3601, LLC EMNSYSTO ITCRR OPOACT\nS412232-3 StreamCo East Collins, LLC NIC .ENS,AGTERSTEDRI EGNOALITNA | char_count: 2296 | word_count: 282 | anomalies: {\"page_number\":629,\"source\":\"MERGED-Kettler\",\"address_clusters\":[],\"entity_variations\":[],\"date_sequences\":[],\"suspicious_patterns\":[]}",
  "embedding": [
    -0.09773261100053787,
    -0.0274458397179842,
    -0.029230106621980667,
    -0.04921625182032585,
    0.033360909670591354,
    -0.029351867735385895,
    0.02324588969349861,
    0.07399492710828781,
    -0.011924058198928833,
    0.01082979328930378,
    0.05895114690065384,
    -0.0005152891390025616,
    0.05205509066581726,
    0.00016537861665710807,
    -0.15679346024990082,
    -0.06658124178647995,
    -0.016681646928191185,
    -0.030392568558454514,
    -0.015225275419652462,
    -0.0057250927202403545,
    0.009085709229111671,
    0.08599007874727249,
    -0.07591243088245392,
    -0.055031098425388336,
    0.01776721701025963,
    0.09140921384096146,
    -0.06172126531600952,
    0.014297271147370338,
    -0.09722252190113068,
    -0.12864361703395844,
    0.03052510693669319,
    0.03691939264535904,
    0.01821873150765896,
    0.01823551580309868,
    0.0998198464512825,
    0.01915167085826397,
    -0.07154553383588791,
    0.007628967985510826,
    -0.00431546475738287,
    -0.03923993930220604,
    0.05992722883820534,
    -0.05098222196102142,
    0.07506692409515381,
    0.054255831986665726,
    0.022112157195806503,
    0.016992053017020226,
    -0.09860311448574066,
    -0.05690691992640495,
    -0.03231394663453102,
    0.0031444174237549305,
    0.03727029263973236,
    0.032659195363521576,
    0.0007019973127171397,
    0.010618261992931366,
    -0.016117751598358154,
    -0.07528667151927948,
    -0.06951567530632019,
    -0.08971738070249557,
    0.02479758858680725,
    0.0033980298321694136,
    0.0744471326470375,
    -0.02519330009818077,
    0.004326370544731617,
    -0.03143315762281418,
    0.025197727605700493,
    0.02087341621518135,
    0.013218570500612259,
    -0.09687080979347229,
    -0.03307405859231949,
    -0.04379590228199959,
    -0.01831381395459175,
    0.059252653270959854,
    0.04025089368224144,
    0.10677489638328552,
    0.017594479024410248,
    0.08224446326494217,
    0.03390387073159218,
    -0.05637108534574509,
    0.07805383950471878,
    -0.055554602295160294,
    -0.0034726106096059084,
    0.02451850101351738,
    0.05613895133137703,
    0.05544857680797577,
    0.055065516382455826,
    0.03738376870751381,
    -0.02215711399912834,
    -0.026068082079291344,
    0.08818145841360092,
    0.004703823011368513,
    0.08444412052631378,
    0.05708866938948631,
    -0.03756558150053024,
    0.0466625951230526,
    -0.03628264367580414,
    0.013991366140544415,
    0.04412854090332985,
    0.026784371584653854,
    -0.13887207210063934,
    0.03039795719087124,
    -0.032093655318021774,
    -0.010556651279330254,
    -0.006607357412576675,
    -0.051196254789829254,
    -0.07366911321878433,
    -0.060882747173309326,
    0.02094968408346176,
    0.023711085319519043,
    -0.0067913890816271305,
    -0.07165275514125824,
    0.001110085635446012,
    0.014055605046451092,
    -0.011241071857511997,
    -0.029644794762134552,
    0.001926750992424786,
    -0.04020899906754494,
    0.027508415281772614,
    -0.05148389935493469,
    0.059005457907915115,
    -0.024005703628063202,
    -0.024736767634749413,
    -0.04147569462656975,
    -0.06510581821203232,
    -0.016450170427560806,
    -0.054855309426784515,
    -0.006463144905865192,
    0.0019255881197750568,
    2.3636365800490413e-32,
    -0.031764861196279526,
    -0.006229103077203035,
    0.000695189693942666,
    0.006920406129211187,
    -0.00344667281024158,
    -0.010077224113047123,
    -0.009195617400109768,
    0.006453054957091808,
    -0.017112035304307938,
    0.0014927672455087304,
    -0.14897902309894562,
    -0.042588409036397934,
    -0.0055041261948645115,
    -0.035289015620946884,
    -0.023012343794107437,
    0.00527033070102334,
    0.09598690271377563,
    -0.012904409319162369,
    -0.06313298642635345,
    -0.08306829631328583,
    0.04270036518573761,
    0.05228373408317566,
    -0.050702549517154694,
    -0.034935444593429565,
    0.04392010718584061,
    0.06799278408288956,
    -0.0914558470249176,
    -0.06318420171737671,
    0.04731740057468414,
    0.031137041747570038,
    0.04989974945783615,
    0.03228941187262535,
    -0.07595611363649368,
    0.01755249686539173,
    0.001697761588729918,
    -0.01714172028005123,
    -0.000518673739861697,
    -0.04640300199389458,
    0.00029223746969364583,
    -0.006401251070201397,
    0.026325419545173645,
    0.04930436611175537,
    -0.03315271437168121,
    0.04593075439333916,
    0.044482212513685226,
    -0.035870421677827835,
    -0.05294779688119888,
    0.0429949127137661,
    0.010183924809098244,
    0.07470811903476715,
    -0.0239629615098238,
    0.04854530096054077,
    0.015318508259952068,
    0.043901219964027405,
    -0.04322490468621254,
    -0.016984498128294945,
    -0.028517670929431915,
    0.003925243392586708,
    0.06471721827983856,
    0.049424171447753906,
    0.03223027288913727,
    0.07642072439193726,
    -0.013821671716868877,
    -0.08790836483240128,
    0.07526572793722153,
    -0.052346862852573395,
    -0.022133098915219307,
    -0.02761778235435486,
    -0.07013632357120514,
    -0.006963467225432396,
    -0.019719602540135384,
    -0.08962284028530121,
    0.13242803514003754,
    0.042183272540569305,
    -0.004191259387880564,
    -0.043571289628744125,
    -0.025093356147408485,
    0.051208678632974625,
    -0.05216287076473236,
    -0.010553879663348198,
    -0.01082876231521368,
    -0.033840909600257874,
    -0.05181271210312843,
    -0.059573400765657425,
    -0.03594750538468361,
    -0.039474006742239,
    -0.023096956312656403,
    -0.06129029020667076,
    0.009333633817732334,
    -0.005485554225742817,
    0.0469389334321022,
    -0.028539758175611496,
    -0.06995990872383118,
    0.015144094824790955,
    -0.12316485494375229,
    -2.3092410197751215e-32,
    -0.036207545548677444,
    -0.026885036379098892,
    -0.006035361904650927,
    0.005570989102125168,
    -0.05038134381175041,
    -0.007822604849934578,
    -0.017124800011515617,
    0.01756489835679531,
    0.05325823649764061,
    -0.005504995118826628,
    0.10897129029035568,
    0.08120978623628616,
    0.04218802973628044,
    -0.1113329753279686,
    0.04912272468209267,
    0.029348772019147873,
    -0.02951478399336338,
    0.035902295261621475,
    -0.006390496622771025,
    0.043235864490270615,
    -0.07776770740747452,
    0.14189597964286804,
    -0.003068590769544244,
    0.04823155328631401,
    0.005664610303938389,
    0.0643090158700943,
    0.014189768582582474,
    0.02876942604780197,
    0.028854597359895706,
    0.07683191448450089,
    0.0405416302382946,
    0.03983938321471214,
    -0.04770509526133537,
    0.1483466923236847,
    -0.10328890383243561,
    -0.039011675864458084,
    0.06374598294496536,
    -0.06376320868730545,
    -0.030612517148256302,
    -0.008113335818052292,
    0.11039161682128906,
    0.0022097101900726557,
    0.0008140965364873409,
    0.04384729638695717,
    -0.012870384380221367,
    0.018926937133073807,
    0.04816931486129761,
    -0.02284124493598938,
    0.06385346502065659,
    0.0016098208725452423,
    0.09330925345420837,
    0.011011367663741112,
    -0.038401003926992416,
    0.05008126050233841,
    0.0701129287481308,
    0.02872924879193306,
    0.01667136326432228,
    -0.04823945462703705,
    -0.11733193695545197,
    -0.08051076531410217,
    0.10053545236587524,
    0.00032853218726813793,
    -0.035351064056158066,
    -0.01344162318855524,
    0.10928412526845932,
    0.03225695341825485,
    -0.048471298068761826,
    0.05120183154940605,
    0.06888193637132645,
    -0.08656880259513855,
    -0.02187454327940941,
    -0.008875252678990364,
    -0.05332878604531288,
    -0.07410886138677597,
    0.09425146132707596,
    -0.01882263459265232,
    -0.029677538201212883,
    -0.02804713137447834,
    -0.06707855314016342,
    -0.04939393699169159,
    -0.005847018677741289,
    -0.0346590057015419,
    0.04754776880145073,
    0.02137300930917263,
    -0.00044319985317997634,
    -0.07259869575500488,
    -0.003335479414090514,
    0.04153437167406082,
    -0.01031190250068903,
    -0.029625795781612396,
    -0.06117464229464531,
    -0.004168516956269741,
    0.003218024503439665,
    0.1315312385559082,
    0.046691276133060455,
    -7.046164540724931e-08,
    0.0012204584199935198,
    -0.0002101190184475854,
    0.0060323746874928474,
    -0.04375622421503067,
    0.04076990485191345,
    -0.027037223801016808,
    0.045198652893304825,
    0.021896343678236008,
    0.004946745932102203,
    -0.019591184332966805,
    -0.00983696710318327,
    -0.008024074137210846,
    -0.016457684338092804,
    -0.06032181158661842,
    0.0929344892501831,
    -0.049053601920604706,
    -0.058755431324243546,
    0.023029977455735207,
    -0.05273973196744919,
    -0.014041419140994549,
    -0.028490282595157623,
    -0.04401511698961258,
    0.017367735505104065,
    -0.06377376616001129,
    -0.005476662889122963,
    -0.032230038195848465,
    0.05827871710062027,
    0.05779609829187393,
    -0.023903656750917435,
    0.027601614594459534,
    -0.047776661813259125,
    -0.040653377771377563,
    0.020060399547219276,
    -0.013733926229178905,
    0.013373952358961105,
    0.021119695156812668,
    -0.005108423996716738,
    -0.008724604733288288,
    0.06562885642051697,
    -0.0029792909044772387,
    -0.07550477236509323,
    0.013928518630564213,
    -0.04691010341048241,
    0.07350403815507889,
    -0.0069198631681501865,
    0.022862324491143227,
    -0.009222419932484627,
    0.007483366411179304,
    0.05603061988949776,
    -0.13397495448589325,
    -0.06178222596645355,
    0.021478664129972458,
    -0.0017246593488380313,
    -0.012745064683258533,
    -0.10291445255279541,
    -0.0469692125916481,
    -0.029606720432639122,
    0.025526514276862144,
    0.04403167590498924,
    0.013540227897465229,
    0.043202824890613556,
    -0.09963894635438919,
    0.027520615607500076,
    -0.05100921913981438
  ]
}