{
  "metadata": {
    "source": "pdf_analysis",
    "created": "2025-12-11T00:33:54.064888",
    "file_path": "/Users/machine/Documents/kettler-data-analysis/research/texas/pdf_analysis/lariat-merged/pages/page_0135.json",
    "has_embedding": true
  },
  "data": {
    "page_number": 135,
    "text": "iFling#8:03790640D ocumen#1t:38428169000i2Fl en72dO /22 /024re ceivedbU y pload\no8Frm 01 us.eecfid for ofsrve reesehi scTpa\n1)1sd 05/vie(Re\no: tetacin dupl itSiubm\nSecretary of State\nP.O. Box 13697\nntemetnsaiton for ReitacAippl\nAustin, TX 78711-3697\n512 463-5555 Asdei o Sts teAquetnd Re\nAX 512 463-5709:F uretx FiaorfeT\nonsitnsruc it Se:eng FeieFli\nCL, LALNIC MTTANAGMNEETs BA i:INeBRIDmG My naEIDt-Aint eheT1.\nrsfe fromf ditha tem nar aon undeitsrasgitt ren iiao obtd tre wsquita rehay ttintgn eis forey i atint eheT\nsd i:resesgity i retint eheh tr wc undehiem naheT. boved aet saetm nalgae lhet\ns 803790640 i:etry of saattre scheey by ttint eheso tr isd tbeue numel fiheT2.\n202224/ 06/ on:x CodeaT sonshe provii of ther td undevoked or reety wsita forfeint eheT3.\ndmm/dyyyy/\nhTeu ndersignedrehoe qhtefrfiuuta treorees t r vostcaihtoteebano niy ese si ftt tdae n,dcei rt4 . (cid:222) es\n:that\nsnd ha ax CodeaT her 171 of tepthad by cresqui i retha tport rentnqueilh decad eesly ha fitint eheT. a\nonitacispplhi a of temi the tts a i duethand tposd ames iretentnd i, aytlnax, pea the for tnteym padeam\nnd ar;ette lencraaelx cad thecatt ahed by tencdesvia e\nrsd peon wsrsgnea: undeiheon, titavoc or reureti of forfeet dab. Ohen t\noron;itorpora csl or profesonati-profid forem-nabove aher of tdeholor or srethacre, direcfin of짜 a.\n. oron;itsa asislocd profesonaeim-nabove aher of tbemer or mdehol, srehaortcre, direcfin ofa\nan officer, director, or member of the above-named nonprofit corporation; or\na member or manager of the above-named limited liability company; or\na partner of the above-named limited partnership; or\na trustee or beneficial owner of the above-named statutory or business trust.\nngsion or Fliitanted Dumreocqui RelonaiAtddi\n짜 Comptroller of Public Accounts Tax Clearance Letter\nis no longteal Consent or Amendment to Certificate of Formation or Registration (Required when emity name\noniutcxeE\nwhea for tposd by lsmee iitlna pehend t, auryrjy of petlnasr pere undealcd dersgne undeiheT\nkeao md tezhorisutd i arsgne undeihe ttha, tntensrum itnteuduls or fraley fallarietas msison of aubmi\nwsea notncraaelx ca tthand t, atcorrend c arue tren aired heneiasontnt cemet sahet ttha ts:squethi ret\non.itanform inteuduls or fraleng fadid by provineiaobt\n202417/ 7/:eDta\nV-PSICEREIP RA:S MANC, CHALRISGR, L PIPEHLSIL, BY\nonsi)tnsrucrs itd peon (seeezhoriut of auretSgnai\nCHRIS PIPHLSIL\nPrineyptdote r dn aameo uh ftorizedp erson\no8Frm 01 3",
    "char_count": 2450,
    "word_count": 375,
    "anomalies": {
      "page_number": 135,
      "source": "lariat-merged",
      "address_clusters": [],
      "entity_variations": [],
      "date_sequences": [],
      "suspicious_patterns": []
    }
  },
  "text_representation": "page_number: 135 | text: iFling#8:03790640D ocumen#1t:38428169000i2Fl en72dO /22 /024re ceivedbU y pload\no8Frm 01 us.eecfid for ofsrve reesehi scTpa\n1)1sd 05/vie(Re\no: tetacin dupl itSiubm\nSecretary of State\nP.O. Box 13697\nntemetnsaiton for ReitacAippl\nAustin, TX 78711-3697\n512 463-5555 Asdei o Sts teAquetnd Re\nAX 512 463-5709:F uretx FiaorfeT\nonsitnsruc it Se:eng FeieFli\nCL, LALNIC MTTANAGMNEETs BA i:INeBRIDmG My naEIDt-Aint eheT1.\nrsfe fromf ditha tem nar aon undeitsrasgitt ren iiao obtd tre wsquita rehay ttintgn eis forey i atint eheT\nsd i:resesgity i retint eheh tr wc undehiem naheT. boved aet saetm nalgae lhet\ns 803790640 i:etry of saattre scheey by ttint eheso tr isd tbeue numel fiheT2.\n202224/ 06/ on:x CodeaT sonshe provii of ther td undevoked or reety wsita forfeint eheT3.\ndmm/dyyyy/\nhTeu ndersignedrehoe qhtefrfiuuta treorees t r vostcaihtoteebano niy ese si ftt tdae n,dcei rt4 . (cid:222) es\n:that\nsnd ha ax CodeaT her 171 of tepthad by cresqui i retha tport rentnqueilh decad eesly ha fitint eheT. a\nonitacispplhi a of temi the tts a i duethand tposd ames iretentnd i, aytlnax, pea the for tnteym padeam\nnd ar;ette lencraaelx cad thecatt ahed by tencdesvia e\nrsd peon wsrsgnea: undeiheon, titavoc or reureti of forfeet dab. Ohen t\noron;itorpora csl or profesonati-profid forem-nabove aher of tdeholor or srethacre, direcfin of짜 a.\n. oron;itsa asislocd profesonaeim-nabove aher of tbemer or mdehol, srehaortcre, direcfin ofa\nan officer, director, or member of the above-named nonprofit corporation; or\na member or manager of the above-named limited liability company; or\na partner of the above-named limited partnership; or\na trustee or beneficial owner of the above-named statutory or business trust.\nngsion or Fliitanted Dumreocqui RelonaiAtddi\n짜 Comptroller of Public Accounts Tax Clearance Letter\nis no longteal Consent or Amendment to Certificate of Formation or Registration (Required when emity name\noniutcxeE\nwhea for tposd by lsmee iitlna pehend t, auryrjy of petlnasr pere undealcd dersgne undeiheT\nkeao md tezhorisutd i arsgne undeihe ttha, tntensrum itnteuduls or fraley fallarietas msison of aubmi\nwsea notncraaelx ca tthand t, atcorrend c arue tren aired heneiasontnt cemet sahet ttha ts:squethi ret\non.itanform inteuduls or fraleng fadid by provineiaobt\n202417/ 7/:eDta\nV-PSICEREIP RA:S MANC, CHALRISGR, L PIPEHLSIL, BY\nonsi)tnsrucrs itd peon (seeezhoriut of auretSgnai\nCHRIS PIPHLSIL\nPrineyptdote r dn aameo uh ftorizedp erson\no8Frm 01 3 | char_count: 2450 | word_count: 375 | anomalies: {\"page_number\":135,\"source\":\"lariat-merged\",\"address_clusters\":[],\"entity_variations\":[],\"date_sequences\":[],\"suspicious_patterns\":[]}",
  "embedding": [
    -0.07323216646909714,
    -0.025285329669713974,
    0.054135750979185104,
    0.00101716339122504,
    -0.05710654333233833,
    0.03934066742658615,
    0.06319040060043335,
    0.0022261179983615875,
    0.02195468172430992,
    -0.04762205109000206,
    0.03526303917169571,
    -0.039003174751996994,
    0.0771753117442131,
    -0.09055217355489731,
    -0.08967496454715729,
    -0.10163163393735886,
    -0.011222370900213718,
    0.02098117582499981,
    -0.05039896070957184,
    -0.024691399186849594,
    0.09984689950942993,
    0.10451463609933853,
    0.009379205293953419,
    -0.005898763425648212,
    0.020039889961481094,
    0.04071449115872383,
    -0.05809865519404411,
    -0.03966674953699112,
    -0.07818232476711273,
    -0.05723315477371216,
    0.0008742731879465282,
    0.07610916346311569,
    -0.05496211722493172,
    -0.01977633312344551,
    0.04861608147621155,
    0.12158471345901489,
    -0.045424237847328186,
    -0.00016904549556784332,
    0.047761719673871994,
    -0.009194746613502502,
    -0.0673275738954544,
    -0.058498211205005646,
    0.021060602739453316,
    0.015159815549850464,
    -0.0019330325303599238,
    -0.05978448688983917,
    -0.045709963887929916,
    0.007469590287655592,
    0.011462667025625706,
    0.023831363767385483,
    -0.0634075477719307,
    0.09468735754489899,
    0.017849087715148926,
    0.05546499788761139,
    0.0005549461930058897,
    -0.00639805942773819,
    0.008730537258088589,
    -0.05338289216160774,
    0.026089288294315338,
    -0.04863505810499191,
    -0.006225478835403919,
    0.0006663069361820817,
    0.013630564324557781,
    -0.03428966924548149,
    -0.07272570580244064,
    -0.029431406408548355,
    -0.10062933713197708,
    -0.026883266866207123,
    0.030110256746411324,
    -0.012178950943052769,
    0.04017212241888046,
    0.03364107757806778,
    -0.010873669758439064,
    0.09521658718585968,
    0.03314429149031639,
    -0.007071431260555983,
    0.03423045948147774,
    -0.0038753231056034565,
    0.0010341532761231065,
    -0.051043860614299774,
    0.04755774512887001,
    -0.02075294218957424,
    0.07143772393465042,
    0.03169288858771324,
    -0.011797619052231312,
    -0.0915537178516388,
    0.026186540722846985,
    0.02076573483645916,
    0.0927574411034584,
    0.030663518235087395,
    0.1074683740735054,
    0.024651329964399338,
    -0.049510031938552856,
    0.005166999530047178,
    -0.010162672959268093,
    -0.06726596504449844,
    -0.08418922871351242,
    0.05582541972398758,
    -0.11090551316738129,
    0.06589780747890472,
    0.04134146869182587,
    0.03173787519335747,
    -0.03810810297727585,
    0.00559942377731204,
    -0.08472838252782822,
    -0.03696872293949127,
    0.033533740788698196,
    -0.034642238169908524,
    0.016247227787971497,
    -0.03289281576871872,
    0.0247727669775486,
    -0.06075979024171829,
    0.009106282144784927,
    -0.021151261404156685,
    -0.022612113505601883,
    0.038545526564121246,
    -0.06619955599308014,
    -0.043445885181427,
    0.01326169166713953,
    -0.008234040811657906,
    0.018988164141774178,
    0.038290753960609436,
    -0.10389875620603561,
    0.0550660714507103,
    -0.058433301746845245,
    -0.06626370549201965,
    0.0029853316955268383,
    2.669208246723615e-32,
    -0.061696916818618774,
    0.09940221160650253,
    0.019968455657362938,
    0.020809678360819817,
    -0.007442556321620941,
    -0.012563062831759453,
    -0.06064663827419281,
    -0.008364181965589523,
    -0.02440384402871132,
    -0.08640709519386292,
    -0.06514840573072433,
    -0.034151095896959305,
    -0.0038863392546772957,
    -0.02978588454425335,
    -0.07841876894235611,
    -0.0548827163875103,
    -0.014116756618022919,
    -0.023291969671845436,
    -0.012611504644155502,
    -0.03254490718245506,
    0.010747164487838745,
    0.06788329035043716,
    0.021026259288191795,
    -0.05004195123910904,
    -0.04874882847070694,
    0.0009487399947829545,
    -0.02457359991967678,
    -0.005997891537845135,
    0.09372767060995102,
    0.06511127203702927,
    0.02823479101061821,
    -0.004401077050715685,
    0.015882527455687523,
    -0.07308459281921387,
    -0.015971334651112556,
    -0.05763518437743187,
    0.06320375949144363,
    -0.12092217803001404,
    -0.07149985432624817,
    -0.02682567574083805,
    -0.0339190773665905,
    0.115667924284935,
    0.008763164281845093,
    0.04509890452027321,
    0.00839588139206171,
    -0.004720958881080151,
    0.015719527378678322,
    0.035315051674842834,
    0.07351447641849518,
    0.08367860317230225,
    0.007562998216599226,
    0.0007528805290348828,
    0.019330104812979698,
    -0.0206617284566164,
    -0.053865812718868256,
    -0.006530663929879665,
    -0.06375221908092499,
    0.028563182801008224,
    0.06293726712465286,
    0.021824795752763748,
    0.05653137341141701,
    -0.0017887854482978582,
    0.05065068230032921,
    -0.03511795774102211,
    -0.023844437673687935,
    -0.007327910978347063,
    -0.051649995148181915,
    -0.025996893644332886,
    0.025074416771531105,
    -0.0038153950590640306,
    -0.07998299598693848,
    0.03352263942360878,
    0.09289395809173584,
    0.03663212060928345,
    -0.0455816350877285,
    0.02087613195180893,
    0.04800683259963989,
    0.011697378940880299,
    -0.01141820102930069,
    0.0032400302588939667,
    -0.04127179831266403,
    -0.0037594037130475044,
    -0.03241876885294914,
    0.016124431043863297,
    0.061073366552591324,
    -0.07921209931373596,
    0.05383244529366493,
    -0.12122572958469391,
    -0.007271729409694672,
    0.08398538082838058,
    0.02375929430127144,
    0.09086191654205322,
    -0.060761019587516785,
    -0.027181629091501236,
    -0.05446213111281395,
    -2.4118171547533698e-32,
    0.0076487562619149685,
    -0.0032585831359028816,
    0.015944093465805054,
    0.0015364643186330795,
    -0.03845047578215599,
    -0.0714634507894516,
    0.033190399408340454,
    0.06528248637914658,
    0.08486375212669373,
    -0.05190938711166382,
    0.02697008289396763,
    -0.0431571826338768,
    0.09012138843536377,
    -0.10721427202224731,
    0.005088740959763527,
    0.0038577518425881863,
    0.054084498435258865,
    0.051981374621391296,
    -0.03918857499957085,
    0.0414709597826004,
    -0.005975764244794846,
    0.04452486336231232,
    -0.07159475237131119,
    0.0363677516579628,
    -0.03189440816640854,
    0.09086605906486511,
    0.058699317276477814,
    -0.008186150342226028,
    -0.07280386239290237,
    -0.05045148357748985,
    0.07226429134607315,
    -0.08033505082130432,
    -0.12861786782741547,
    0.14290164411067963,
    -0.10277109593153,
    0.035821281373500824,
    0.047125909477472305,
    -0.003539609257131815,
    -0.045355670154094696,
    0.08660281449556351,
    0.11600654572248459,
    0.04504422843456268,
    -0.04662024974822998,
    0.005102410912513733,
    -0.024343367666006088,
    -0.07348734885454178,
    -0.028906743973493576,
    0.021422868594527245,
    0.04271381348371506,
    -0.05597969889640808,
    0.08335398882627487,
    -0.017800768837332726,
    -0.055765923112630844,
    0.006937155034393072,
    0.05341862887144089,
    -0.037473928183317184,
    -0.020119979977607727,
    -0.0404307097196579,
    -0.043992429971694946,
    -0.0721127837896347,
    0.03676605969667435,
    0.054085250943899155,
    0.014047711156308651,
    -0.06805507838726044,
    0.12030353397130966,
    -0.03650185838341713,
    0.017441585659980774,
    0.0009085051133297384,
    0.07588514685630798,
    -0.02038855105638504,
    0.03953305631875992,
    -0.07182648777961731,
    -0.10698108375072479,
    -0.08714891225099564,
    0.0903187245130539,
    0.09610400348901749,
    -0.01807985082268715,
    -0.018171818926930428,
    -0.09710612893104553,
    0.04270801320672035,
    -0.03724919632077217,
    -0.004832771606743336,
    0.013804275542497635,
    0.013200461864471436,
    0.017262738198041916,
    0.08708853274583817,
    0.012789899483323097,
    0.05811276659369469,
    0.08065629005432129,
    0.02396986074745655,
    -0.02332521602511406,
    0.007744764909148216,
    0.07314798980951309,
    0.0710495337843895,
    0.0034130767453461885,
    -7.65489289733523e-08,
    -0.032863542437553406,
    -0.019658247008919716,
    -0.05507216230034828,
    0.0029611841309815645,
    0.010930757969617844,
    -0.0301996897906065,
    -0.015768490731716156,
    -0.06604845076799393,
    -0.0743163451552391,
    -0.011479162611067295,
    0.014250633306801319,
    -0.011011848226189613,
    -0.07959708571434021,
    -0.08530336618423462,
    0.04511399194598198,
    0.015676068142056465,
    -0.009410175494849682,
    0.038988955318927765,
    -0.055272914469242096,
    -0.028975028544664383,
    -0.011328335851430893,
    -0.0059243179857730865,
    -0.03092019259929657,
    0.03547694906592369,
    -0.06043389067053795,
    0.023633090779185295,
    0.003653026884421706,
    -0.0069230953231453896,
    0.0023951528128236532,
    -0.0815521627664566,
    0.03349148482084274,
    -0.056321561336517334,
    -0.042540598660707474,
    -0.07069114595651627,
    -0.0426323376595974,
    0.01975279487669468,
    -0.043205395340919495,
    0.012436697259545326,
    0.03722228482365608,
    0.08411163836717606,
    0.07872647047042847,
    0.03260968625545502,
    0.003866792656481266,
    0.044597987085580826,
    -0.027627846226096153,
    0.0014753376599401236,
    0.0010504873935133219,
    0.030065391212701797,
    0.017749112099409103,
    -0.07190924882888794,
    -0.08522897213697433,
    -0.025986703112721443,
    -0.006259164772927761,
    0.042850691825151443,
    -0.008155273273587227,
    -0.02972976677119732,
    -0.001999756321310997,
    0.04134272411465645,
    -0.00380540918558836,
    0.026337377727031708,
    0.06815017014741898,
    -0.007714277133345604,
    -0.03488347306847572,
    -0.028685303404927254
  ]
}