{
  "metadata": {
    "source": "pdf_analysis",
    "created": "2025-12-11T00:52:01.740411",
    "file_path": "/Users/machine/Documents/kettler-data-analysis/research/texas/pdf_analysis/lariat-merged/pages/page_0166.json",
    "has_embedding": true
  },
  "data": {
    "page_number": 166,
    "text": "19117750111\npersons shall look solely to the Corporation for the payment of any claim under or for the\nperformance of that instrument. The omission of the foregoing exculpatory language from\nany instrument shall not affect the validity or enforceability of such instrument and shall not\nrender any director, officer, employee or agent liable thereunder to any third party, nor shall\nany director, officer, employee or agent of the Corporation be liable to anyone for such\nomission. No amendment of these Articles of Incorporation or repeal of any of its provisions\nshall limit or eliminate the limitation of liability provided to directors and officers hereunder\nwith respect to any act or omission occurring prior to such amendment or repeal.\n(c) The Corporation shall indemnify (i) its directors and officers, whether\nserving the Corporation or at its request any other entity, to the full extent required or\npermitted by the laws of the State of Texas applicable to ordinary business corporations now\nor hereafter in force, including the advance of expenses under the procedures and to the full\nextent permitted by such laws, and ii) the employees and agents of the Corporation to such\nextent as shall be authorized by the directors or the bylaws of the Corporation and as\npermitted by law. Nothing contained herein shall be construed to protect any person against\nany liability to the extent such protection would violate Texas statutory or decisional law\napplicable to corporations organized in Texas The foregoing rights of indemnification shall\nnot be exclusive of any other rights to which whose seeking indemnification may be entitled.\nThe directors may take such action as is necessary to carry out these indemnification\nemio t temi tnd fromemnd a approve, adopto ad tpowresmexpresy e elresonsnd aprovii a\nrsonsheng sh provii or sh furtiucucntemeplsmt icraonsontwi or cassutsh byl, reoluc\nselcAirts hee of tntendme. Nmo awad by lettirm pey bessant a memngerraon aitacfinimndei\nofght rihe tetnaimil or etimi lssonslt provii slny of iha of alapeon or reitorporaof Inc\nindemnification provided hereunder with respect to acts or omissions occurring prior to such\namendmeoren r pteal.\ninArtclIcoeo rps foraitono rSuboajt nee y xpctrereriiss stctonihs nte se\nadopted by the directors in the bylaws or by resolution or set forth in Article 2.35-1 of the\nTexas Business Corporation Act, as amended, the Corporation (which, for purposes of this\nArticle 7(d), shall include the Corporation and any of its subsidiaries) may enter into any\ncontract or transaction of any kind with any person, including any director, officer, employee\nI agent of the Corporation or any person affiliated with the Corporation or a director\nfficer, employee or agent of the Corporation, whether or not any of them has a financia\ninterest in such transaction.\n8.\nhreaTeste dh tdteireo nss fiitalre giestredo f (cid:222) hteCceo o frporaitonihaeo nteStt f\nLe aCsts olinaBos ulevaSurd ie3rvi,t 5In0 g,,2 2ru,2Wst Texashs allba eGb leRs esidenital T\nhTei niitalre giestredah gteCeo on frptoraitosuna cha t ddreshss allb eexa7s 5039 .T\nWillam M. Hammond.\n3",
    "char_count": 3130,
    "word_count": 496,
    "anomalies": {
      "page_number": 166,
      "source": "lariat-merged",
      "address_clusters": [],
      "entity_variations": [],
      "date_sequences": [],
      "suspicious_patterns": []
    }
  },
  "text_representation": "page_number: 166 | text: 19117750111\npersons shall look solely to the Corporation for the payment of any claim under or for the\nperformance of that instrument. The omission of the foregoing exculpatory language from\nany instrument shall not affect the validity or enforceability of such instrument and shall not\nrender any director, officer, employee or agent liable thereunder to any third party, nor shall\nany director, officer, employee or agent of the Corporation be liable to anyone for such\nomission. No amendment of these Articles of Incorporation or repeal of any of its provisions\nshall limit or eliminate the limitation of liability provided to directors and officers hereunder\nwith respect to any act or omission occurring prior to such amendment or repeal.\n(c) The Corporation shall indemnify (i) its directors and officers, whether\nserving the Corporation or at its request any other entity, to the full extent required or\npermitted by the laws of the State of Texas applicable to ordinary business corporations now\nor hereafter in force, including the advance of expenses under the procedures and to the full\nextent permitted by such laws, and ii) the employees and agents of the Corporation to such\nextent as shall be authorized by the directors or the bylaws of the Corporation and as\npermitted by law. Nothing contained herein shall be construed to protect any person against\nany liability to the extent such protection would violate Texas statutory or decisional law\napplicable to corporations organized in Texas The foregoing rights of indemnification shall\nnot be exclusive of any other rights to which whose seeking indemnification may be entitled.\nThe directors may take such action as is necessary to carry out these indemnification\nemio t temi tnd fromemnd a approve, adopto ad tpowresmexpresy e elresonsnd aprovii a\nrsonsheng sh provii or sh furtiucucntemeplsmt icraonsontwi or cassutsh byl, reoluc\nselcAirts hee of tntendme. Nmo awad by lettirm pey bessant a memngerraon aitacfinimndei\nofght rihe tetnaimil or etimi lssonslt provii slny of iha of alapeon or reitorporaof Inc\nindemnification provided hereunder with respect to acts or omissions occurring prior to such\namendmeoren r pteal.\ninArtclIcoeo rps foraitono rSuboajt nee y xpctrereriiss stctonihs nte se\nadopted by the directors in the bylaws or by resolution or set forth in Article 2.35-1 of the\nTexas Business Corporation Act, as amended, the Corporation (which, for purposes of this\nArticle 7(d), shall include the Corporation and any of its subsidiaries) may enter into any\ncontract or transaction of any kind with any person, including any director, officer, employee\nI agent of the Corporation or any person affiliated with the Corporation or a director\nfficer, employee or agent of the Corporation, whether or not any of them has a financia\ninterest in such transaction.\n8.\nhreaTeste dh tdteireo nss fiitalre giestredo f (cid:222) hteCceo o frporaitonihaeo nteStt f\nLe aCsts olinaBos ulevaSurd ie3rvi,t 5In0 g,,2 2ru,2Wst Texashs allba eGb leRs esidenital T\nhTei niitalre giestredah gteCeo on frptoraitosuna cha t ddreshss allb eexa7s 5039 .T\nWillam M. Hammond.\n3 | char_count: 3130 | word_count: 496 | anomalies: {\"page_number\":166,\"source\":\"lariat-merged\",\"address_clusters\":[],\"entity_variations\":[],\"date_sequences\":[],\"suspicious_patterns\":[]}",
  "embedding": [
    -0.08014854788780212,
    0.04407718777656555,
    0.05049099400639534,
    -0.0037122045177966356,
    -0.0438205823302269,
    0.05338129773736,
    0.03361854702234268,
    -0.032555706799030304,
    -0.005440098699182272,
    -0.05872315913438797,
    0.13635976612567902,
    0.009641743265092373,
    0.0323173962533474,
    -0.10340802371501923,
    -0.0054842280223965645,
    -0.05177300423383713,
    0.061205752193927765,
    0.08074375241994858,
    0.010003376752138138,
    0.028737127780914307,
    0.06233189254999161,
    -0.023027092218399048,
    -0.09251399338245392,
    0.09319380670785904,
    0.013310635462403297,
    0.00025620285305194557,
    -0.035360194742679596,
    -0.019880985841155052,
    -0.046223197132349014,
    -0.04529514163732529,
    -0.03592866286635399,
    -0.0024638259783387184,
    0.049002405256032944,
    -0.008641870692372322,
    0.11819376051425934,
    -0.001992742298170924,
    0.026285164058208466,
    -0.047244731336832047,
    -0.022511161863803864,
    -0.02982041984796524,
    -0.047701578587293625,
    0.0020684816408902407,
    0.001698637381196022,
    0.03063202276825905,
    -0.056610628962516785,
    -0.04255741834640503,
    -0.01051357202231884,
    -0.004203967284411192,
    -0.05072120577096939,
    0.03411921486258507,
    -0.004482676740735769,
    0.0294126495718956,
    0.03611265867948532,
    0.07116615772247314,
    0.0058829523622989655,
    -0.09882058948278427,
    -0.09277009963989258,
    -0.052606407552957535,
    -0.002278367057442665,
    0.06507086008787155,
    0.005492896307259798,
    0.034118689596652985,
    0.006801813840866089,
    0.02630530670285225,
    0.03806393966078758,
    0.04520444944500923,
    0.033682942390441895,
    -0.09664396941661835,
    -0.03969500958919525,
    0.019450295716524124,
    0.046977028250694275,
    -0.04524197429418564,
    -0.03351321816444397,
    0.06305698305368423,
    0.01003148965537548,
    0.02992427349090576,
    -0.00522294407710433,
    0.05211381986737251,
    0.013674315996468067,
    -0.12429462373256683,
    0.01338721252977848,
    0.08069372922182083,
    0.034826088696718216,
    -0.09326111525297165,
    -0.12881505489349365,
    -0.01948518306016922,
    0.04196105897426605,
    0.04402646794915199,
    0.0670810416340828,
    0.06824969500303268,
    0.07677140831947327,
    0.014480074867606163,
    0.005691151134669781,
    -0.08897311985492706,
    0.10932723432779312,
    -0.009722805581986904,
    -0.03934696689248085,
    -0.05955391377210617,
    0.03924480080604553,
    0.031094292178750038,
    0.03711696341633797,
    0.03913374990224838,
    -0.025231558829545975,
    -0.0010056821629405022,
    -0.040073759853839874,
    -0.030623676255345345,
    -0.011856337077915668,
    -0.07543052732944489,
    -0.011442884802818298,
    -0.029571421444416046,
    0.03756363317370415,
    -0.03890983387827873,
    -0.022487839683890343,
    -0.056396860629320145,
    0.00019039107428397983,
    0.030284471809864044,
    -0.023852653801441193,
    0.05233050510287285,
    0.06652345508337021,
    -0.0939583107829094,
    0.005400214344263077,
    0.07379767298698425,
    -0.00997319258749485,
    0.04747956991195679,
    -0.04634379222989082,
    0.0034678566735237837,
    -0.08662312477827072,
    3.005853482080802e-33,
    -0.08321032673120499,
    0.0038006596732884645,
    -0.025273485109210014,
    0.020151151344180107,
    0.0076950010843575,
    -0.011564353480935097,
    0.06343934684991837,
    -0.012437427416443825,
    -0.038603831082582474,
    0.04411507397890091,
    -0.004520334303379059,
    0.012672803364694118,
    0.02303721010684967,
    -0.07128281891345978,
    0.010845296084880829,
    -0.008025470189750195,
    0.03684091195464134,
    0.0639079362154007,
    0.11276955157518387,
    -0.016740690916776657,
    0.04625455290079117,
    0.014501987025141716,
    -0.03771646320819855,
    0.03051314316689968,
    -0.036484044045209885,
    0.046141453087329865,
    -0.0850304588675499,
    -0.04323955997824669,
    -0.04246615990996361,
    0.022861337289214134,
    0.04052042216062546,
    0.005398674868047237,
    0.06969443708658218,
    0.056072503328323364,
    0.046249665319919586,
    0.01847107522189617,
    -0.03636043891310692,
    -0.03595384210348129,
    -0.03301619738340378,
    -0.034802623093128204,
    -0.07683530449867249,
    0.03942115977406502,
    0.020721323788166046,
    -0.007322392892092466,
    -0.05003875121474266,
    -0.07104910165071487,
    -0.008692890405654907,
    0.0680437982082367,
    0.027107087895274162,
    0.057859115302562714,
    0.02435482107102871,
    0.009055599570274353,
    0.08055026829242706,
    -0.051144376397132874,
    0.01601415127515793,
    -0.03747156262397766,
    -0.034680724143981934,
    0.003691995982080698,
    -0.030554836615920067,
    -0.05794171243906021,
    0.03051070123910904,
    0.046237677335739136,
    -0.06799141317605972,
    0.029784895479679108,
    -0.05344197154045105,
    -0.03770621865987778,
    -0.041772712022066116,
    -0.01274050585925579,
    0.06898298114538193,
    -0.07914996892213821,
    -0.052361778914928436,
    0.028363801538944244,
    -0.01696888729929924,
    0.013106162659823895,
    -0.05578635260462761,
    0.01514308713376522,
    0.004843815229833126,
    -0.00846959836781025,
    0.057570308446884155,
    0.027059275656938553,
    -0.06387273222208023,
    0.013091453351080418,
    -0.011689884588122368,
    0.006089303642511368,
    0.06406237930059433,
    0.050596922636032104,
    0.008978442288935184,
    0.01401221752166748,
    0.03430056944489479,
    0.05705128237605095,
    0.06645741313695908,
    -0.0068625411950051785,
    -0.038677990436553955,
    0.0847918912768364,
    0.027424046769738197,
    -6.504938148952897e-33,
    0.04846884310245514,
    -0.07276167720556259,
    -0.002830475103110075,
    -0.058111656457185745,
    -0.04744759947061539,
    0.00261984346434474,
    0.01980886235833168,
    -0.04475105181336403,
    -0.018205558881163597,
    -0.11586244404315948,
    -0.022711193189024925,
    -0.047357238829135895,
    -0.020975923165678978,
    -0.07595248520374298,
    -0.03387939929962158,
    0.005341855809092522,
    -0.04297458007931709,
    -0.02794112265110016,
    -0.09920360893011093,
    0.04992984980344772,
    -0.0665278211236,
    -0.003698009066283703,
    0.09893231093883514,
    0.03149276226758957,
    -0.029038799926638603,
    0.014807889237999916,
    0.013706223107874393,
    -0.01596095785498619,
    -0.02414766140282154,
    -0.007438118103891611,
    0.04559938609600067,
    -0.024909116327762604,
    -0.09961800277233124,
    0.010355656035244465,
    -0.030479297041893005,
    -0.10407206416130066,
    0.06859298050403595,
    0.071445532143116,
    0.005147500894963741,
    -0.015019738115370274,
    0.041332636028528214,
    0.10219354927539825,
    0.023328134790062904,
    0.06931637227535248,
    -0.003483631880953908,
    -0.015301799401640892,
    0.06821742653846741,
    -0.11019676178693771,
    0.017779722809791565,
    0.002168121747672558,
    -0.09448262304067612,
    -0.0976438894867897,
    0.032245881855487823,
    0.030385401099920273,
    -0.034621767699718475,
    0.03874504566192627,
    0.09018898755311966,
    -0.02166656032204628,
    0.06949454545974731,
    0.011677899397909641,
    0.05698900669813156,
    0.053636811673641205,
    0.03802613168954849,
    0.07158693671226501,
    0.04333309829235077,
    0.031372543424367905,
    -0.08662964403629303,
    0.03963189199566841,
    0.07920295000076294,
    -0.04951385036110878,
    0.008313479833304882,
    -0.14026640355587006,
    -0.0975320115685463,
    -0.11681937426328659,
    0.03826810047030449,
    0.047952041029930115,
    0.03917143493890762,
    -0.018630441278219223,
    -0.09330414980649948,
    -0.019366232678294182,
    0.061657894402742386,
    0.021375063806772232,
    -0.09411612153053284,
    0.07931728661060333,
    0.0005404520779848099,
    -0.06581460684537888,
    0.07951269298791885,
    0.007186429109424353,
    0.05498792603611946,
    0.070167675614357,
    -0.03529566526412964,
    -0.007103420328348875,
    0.016638580709695816,
    0.060091935098171234,
    -0.07352527976036072,
    -6.091701010291217e-08,
    -0.07578730583190918,
    0.014373516663908958,
    -0.04870090261101723,
    0.006508079823106527,
    0.047166138887405396,
    -0.059703025966882706,
    0.008748588152229786,
    -0.04280651733279228,
    -0.03292366489768028,
    0.01131706964224577,
    0.0920972228050232,
    -0.034095607697963715,
    -0.026347635313868523,
    -0.028857892379164696,
    -0.02116238884627819,
    -0.07129167020320892,
    -0.04851827770471573,
    0.0035272701643407345,
    -0.0608382523059845,
    0.03548550605773926,
    -0.10550195723772049,
    -0.03944316878914833,
    -0.04738977178931236,
    0.02717859484255314,
    -0.023647300899028778,
    -0.01434006541967392,
    -0.05406970903277397,
    0.06069629266858101,
    0.06515919417142868,
    0.06818973273038864,
    0.012634286656975746,
    0.08539926260709763,
    -0.067631796002388,
    -0.023054124787449837,
    -0.0768696740269661,
    -0.04240380600094795,
    -0.03745570778846741,
    0.06731735914945602,
    -0.034729596227407455,
    0.020931869745254517,
    -0.04894556477665901,
    0.024004483595490456,
    -0.005606296472251415,
    0.06161033362150192,
    0.031123120337724686,
    -0.05527377873659134,
    -0.09817823767662048,
    -0.022920219227671623,
    -0.02297152951359749,
    -0.015356767922639847,
    -0.019841905683279037,
    -0.015223054215312004,
    0.005616668611764908,
    0.05263000726699829,
    0.013313887640833855,
    -0.005032461602240801,
    0.10180027782917023,
    0.07705941796302795,
    -0.06302656978368759,
    -0.008562014438211918,
    0.010271737352013588,
    -0.005094624124467373,
    0.08789262920618057,
    -0.03448251634836197
  ]
}